fast_nosql_manager/__init__.py
fast_nosql_manager/test_mongo.py
fast_nosql_manager/abstractions/__init__.py
fast_nosql_manager/abstractions/_mongo.py
fast_nosql_manager/implementations/__init__.py
fast_nosql_manager/implementations/mongo.py
fast_nosql_manager/interfaces/__init__.py
fast_nosql_manager/interfaces/db_config_interface.py
fast_nosql_manager-0.3.4.dist-info/LICENSE
fast_nosql_manager-0.3.4.dist-info/METADATA
fast_nosql_manager-0.3.4.dist-info/WHEEL
fast_nosql_manager-0.3.4.dist-info/top_level.txt
fast_nosql_manager-0.3.4.dist-info/RECORD
