Metadata-Version: 2.1
Name: fast-nosql-manager
Version: 0.3.4
Summary: Um pacote simples para realizar operações no mongoDB
Home-page: https://github.com/OscarSilvaOfficial/fast_nosql_manager
Author: Oscar da Silva
Author-email: oscarkaka222@gmail.com
Classifier: Programming Language :: Python :: 3
Classifier: License :: OSI Approved :: MIT License
Classifier: Operating System :: OS Independent
Requires-Python: >=3.7
License-File: LICENSE
Requires-Dist: pymongo (>=4.1.1)
